repple.py
repple-0.3.4.dist-info/METADATA
repple-0.3.4.dist-info/WHEEL
repple-0.3.4.dist-info/top_level.txt
repple-0.3.4.dist-info/RECORD
