Metadata-Version: 2.1
Name: repple
Version: 0.3.4
Summary: Quick and dirty fdisk-like REPLs
Author-email: vul <wowitsvul@gmail.com>
Project-URL: Homepage, https://github.com/effusiveperiscope/repple
Project-URL: Issues, https://github.com/effusiveperiscope/repple/issues
Classifier: Programming Language :: Python :: 3
Classifier: License :: OSI Approved :: MIT License
Classifier: Operating System :: OS Independent
Requires-Python: >=3.8
